spi.v
module SPI_STATE (
    input clk,
    input reset,
    input [15:0]datain,
    output spi_cs_l,
    output spi_clk,
    output spi_data,
    output [4:0] counter
);
reg [15:0] MOSI;
reg [4:0] count;
reg cs_l;
reg sclk;
reg [2:0]state;
always@(posedge clk or posedge reset)
if(reset)
begin
  MOSI<=16'd0;
  count<=5'd16;
  cs_l<=1'b1;
  sclk<=1'b0;
end
else
begin
  case(state)
  0:begin
    sclk<=1'b0;
    cs_l<=1'b1;
    state<=1;
  end
  1:begin
    sclk<=1'b1;
    cs_l<=1'b0;
    MOSI<=datain[count-1];
    count<=count-1;
    state<=2;
  end
  2:begin
    sclk<=1'b0;
    cs_l<=1'b1;
    if(count>0)
    state<=1;
    else
    begin
      count<=5'd16;
      state<=0;
    end
  end
  default:state<=0;
  endcase
end
assign spi_cs_l=cs_l;
assign spi_clk=sclk;
assign spi_data=MOSI;
assign counter=count;
    
endmodule

spitb.v
`include "spi.v"
`timescale 1ps/1ps
module spitb ();
reg clk,reset;
reg [15:0] datain;
wire spi_cs_l,spi_clk,spi_data;
wire [4:0]counter;
SPI_STATE DUT(.clk(clk),
        .reset(reset),
        .datain(datain),
        .spi_cs_l(spi_cs_l),
        .spi_clk(spi_clk),
        .spi_data(spi_data),
        .counter(counter));
initial begin
    clk=1'b0;
    reset=1'b1;
    datain=16'h0;
end
initial forever begin
    #5 clk=~clk;
end
initial begin
  #10 reset =1'b0;
  #10 datain=16'd2679;
  #335 datain=16'd6876;
  #335 datain=16'd6968;
  #335 datain=16'd9800;
  #335 datain=16'd9975;
end
initial begin
    #2000 $finish;
end
initial begin
    $dumpvars;
    $dumpfile("spi.vcd");
    $monitor("%t,clk=%b,reset=%b,spiclk=%b,spicsl=%b,counter=%d,datain=%d,spidata=%d",$time,clk,reset,spi_clk,spi_cs_l,counter,datain,spi_data);
end
    
endmodule

dump.vcd
$date
	Sat Jan 13 01:05:30 2024
$end
$version
	Icarus Verilog
$end
$timescale
	1ps
$end
$scope module spitb $end
$var wire 1 ! spi_data $end
$var wire 1 " spi_cs_l $end
$var wire 1 # spi_clk $end
$var wire 5 $ counter [4:0] $end
$var reg 1 % clk $end
$var reg 16 & datain [15:0] $end
$var reg 1 ' reset $end
$scope module DUT $end
$var wire 1 % clk $end
$var wire 5 ( counter [4:0] $end
$var wire 16 ) datain [15:0] $end
$var wire 1 ' reset $end
$var wire 1 # spi_clk $end
$var wire 1 " spi_cs_l $end
$var wire 1 ! spi_data $end
$var reg 16 * MOSI [15:0] $end
$var reg 5 + count [4:0] $end
$var reg 1 , cs_l $end
$var reg 1 - sclk $end
$var reg 3 . state [2:0] $end
$upscope $end
$upscope $end
$enddefinitions $end
$comment Show the parameter values. $end
$dumpall
$end
#0
$dumpvars
bx .
0-
1,
b10000 +
b0 *
b0 )
b10000 (
1'
b0 &
0%
b10000 $
0#
1"
0!
$end
#5
1%
#10
0%
0'
#15
b0 .
1%
#20
0%
b101001110111 &
b101001110111 )
#25
b1 .
1%
#30
0%
#35
b10 .
b1111 $
b1111 (
b1111 +
0"
0,
1#
1-
1%
#40
0%
#45
b1 .
1"
1,
0#
0-
1%
#50
0%
#55
b10 .
b1110 $
b1110 (
b1110 +
0"
0,
1#
1-
1%
#60
0%
#65
b1 .
1"
1,
0#
0-
1%
#70
0%
#75
b10 .
b1101 $
b1101 (
b1101 +
0"
0,
1#
1-
1%
#80
0%
#85
b1 .
1"
1,
0#
0-
1%
#90
0%
#95
b10 .
b1100 $
b1100 (
b1100 +
0"
0,
1#
1-
1%
#100
0%
#105
b1 .
1"
1,
0#
0-
1%
#110
0%
#115
1!
b10 .
b1011 $
b1011 (
b1011 +
b1 *
0"
0,
1#
1-
1%
#120
0%
#125
b1 .
1"
1,
0#
0-
1%
#130
0%
#135
0!
b10 .
b1010 $
b1010 (
b1010 +
b0 *
0"
0,
1#
1-
1%
#140
0%
#145
b1 .
1"
1,
0#
0-
1%
#150
0%
#155
1!
b10 .
b1001 $
b1001 (
b1001 +
b1 *
0"
0,
1#
1-
1%
#160
0%
#165
b1 .
1"
1,
0#
0-
1%
#170
0%
#175
0!
b10 .
b1000 $
b1000 (
b1000 +
b0 *
0"
0,
1#
1-
1%
#180
0%
#185
b1 .
1"
1,
0#
0-
1%
#190
0%
#195
b10 .
b111 $
b111 (
b111 +
0"
0,
1#
1-
1%
#200
0%
#205
b1 .
1"
1,
0#
0-
1%
#210
0%
#215
1!
b10 .
b110 $
b110 (
b110 +
b1 *
0"
0,
1#
1-
1%
#220
0%
#225
b1 .
1"
1,
0#
0-
1%
#230
0%
#235
b10 .
b101 $
b101 (
b101 +
0"
0,
1#
1-
1%
#240
0%
#245
b1 .
1"
1,
0#
0-
1%
#250
0%
#255
b10 .
b100 $
b100 (
b100 +
0"
0,
1#
1-
1%
#260
0%
#265
b1 .
1"
1,
0#
0-
1%
#270
0%
#275
0!
b10 .
b11 $
b11 (
b11 +
b0 *
0"
0,
1#
1-
1%
#280
0%
#285
b1 .
1"
1,
0#
0-
1%
#290
0%
#295
1!
b10 .
b10 $
b10 (
b10 +
b1 *
0"
0,
1#
1-
1%
#300
0%
#305
b1 .
1"
1,
0#
0-
1%
#310
0%
#315
b10 .
b1 $
b1 (
b1 +
0"
0,
1#
1-
1%
#320
0%
#325
b1 .
1"
1,
0#
0-
1%
#330
0%
#335
b10 .
b0 $
b0 (
b0 +
0"
0,
1#
1-
1%
#340
0%
#345
b0 .
b10000 $
b10000 (
b10000 +
1"
1,
0#
0-
1%
#350
0%
#355
b1 .
1%
b1101011011100 &
b1101011011100 )
#360
0%
#365
0!
b10 .
b1111 $
b1111 (
b1111 +
b0 *
0"
0,
1#
1-
1%
#370
0%
#375
b1 .
1"
1,
0#
0-
1%
#380
0%
#385
b10 .
b1110 $
b1110 (
b1110 +
0"
0,
1#
1-
1%
#390
0%
#395
b1 .
1"
1,
0#
0-
1%
#400
0%
#405
b10 .
b1101 $
b1101 (
b1101 +
0"
0,
1#
1-
1%
#410
0%
#415
b1 .
1"
1,
0#
0-
1%
#420
0%
#425
1!
b10 .
b1100 $
b1100 (
b1100 +
b1 *
0"
0,
1#
1-
1%
#430
0%
#435
b1 .
1"
1,
0#
0-
1%
#440
0%
#445
b10 .
b1011 $
b1011 (
b1011 +
0"
0,
1#
1-
1%
#450
0%
#455
b1 .
1"
1,
0#
0-
1%
#460
0%
#465
0!
b10 .
b1010 $
b1010 (
b1010 +
b0 *
0"
0,
1#
1-
1%
#470
0%
#475
b1 .
1"
1,
0#
0-
1%
#480
0%
#485
1!
b10 .
b1001 $
b1001 (
b1001 +
b1 *
0"
0,
1#
1-
1%
#490
0%
#495
b1 .
1"
1,
0#
0-
1%
#500
0%
#505
0!
b10 .
b1000 $
b1000 (
b1000 +
b0 *
0"
0,
1#
1-
1%
#510
0%
#515
b1 .
1"
1,
0#
0-
1%
#520
0%
#525
1!
b10 .
b111 $
b111 (
b111 +
b1 *
0"
0,
1#
1-
1%
#530
0%
#535
b1 .
1"
1,
0#
0-
1%
#540
0%
#545
b10 .
b110 $
b110 (
b110 +
0"
0,
1#
1-
1%
#550
0%
#555
b1 .
1"
1,
0#
0-
1%
#560
0%
#565
0!
b10 .
b101 $
b101 (
b101 +
b0 *
0"
0,
1#
1-
1%
#570
0%
#575
b1 .
1"
1,
0#
0-
1%
#580
0%
#585
1!
b10 .
b100 $
b100 (
b100 +
b1 *
0"
0,
1#
1-
1%
#590
0%
#595
b1 .
1"
1,
0#
0-
1%
#600
0%
#605
b10 .
b11 $
b11 (
b11 +
0"
0,
1#
1-
1%
#610
0%
#615
b1 .
1"
1,
0#
0-
1%
#620
0%
#625
b10 .
b10 $
b10 (
b10 +
0"
0,
1#
1-
1%
#630
0%
#635
b1 .
1"
1,
0#
0-
1%
#640
0%
#645
0!
b10 .
b1 $
b1 (
b1 +
b0 *
0"
0,
1#
1-
1%
#650
0%
#655
b1 .
1"
1,
0#
0-
1%
#660
0%
#665
b10 .
b0 $
b0 (
b0 +
0"
0,
1#
1-
1%
#670
0%
#675
b0 .
b10000 $
b10000 (
b10000 +
1"
1,
0#
0-
1%
#680
0%
#685
b1 .
1%
#690
0%
b1101100111000 &
b1101100111000 )
#695
b10 .
b1111 $
b1111 (
b1111 +
0"
0,
1#
1-
1%
#700
0%
#705
b1 .
1"
1,
0#
0-
1%
#710
0%
#715
b10 .
b1110 $
b1110 (
b1110 +
0"
0,
1#
1-
1%
#720
0%
#725
b1 .
1"
1,
0#
0-
1%
#730
0%
#735
b10 .
b1101 $
b1101 (
b1101 +
0"
0,
1#
1-
1%
#740
0%
#745
b1 .
1"
1,
0#
0-
1%
#750
0%
#755
1!
b10 .
b1100 $
b1100 (
b1100 +
b1 *
0"
0,
1#
1-
1%
#760
0%
#765
b1 .
1"
1,
0#
0-
1%
#770
0%
#775
b10 .
b1011 $
b1011 (
b1011 +
0"
0,
1#
1-
1%
#780
0%
#785
b1 .
1"
1,
0#
0-
1%
#790
0%
#795
0!
b10 .
b1010 $
b1010 (
b1010 +
b0 *
0"
0,
1#
1-
1%
#800
0%
#805
b1 .
1"
1,
0#
0-
1%
#810
0%
#815
1!
b10 .
b1001 $
b1001 (
b1001 +
b1 *
0"
0,
1#
1-
1%
#820
0%
#825
b1 .
1"
1,
0#
0-
1%
#830
0%
#835
b10 .
b1000 $
b1000 (
b1000 +
0"
0,
1#
1-
1%
#840
0%
#845
b1 .
1"
1,
0#
0-
1%
#850
0%
#855
0!
b10 .
b111 $
b111 (
b111 +
b0 *
0"
0,
1#
1-
1%
#860
0%
#865
b1 .
1"
1,
0#
0-
1%
#870
0%
#875
b10 .
b110 $
b110 (
b110 +
0"
0,
1#
1-
1%
#880
0%
#885
b1 .
1"
1,
0#
0-
1%
#890
0%
#895
1!
b10 .
b101 $
b101 (
b101 +
b1 *
0"
0,
1#
1-
1%
#900
0%
#905
b1 .
1"
1,
0#
0-
1%
#910
0%
#915
b10 .
b100 $
b100 (
b100 +
0"
0,
1#
1-
1%
#920
0%
#925
b1 .
1"
1,
0#
0-
1%
#930
0%
#935
b10 .
b11 $
b11 (
b11 +
0"
0,
1#
1-
1%
#940
0%
#945
b1 .
1"
1,
0#
0-
1%
#950
0%
#955
0!
b10 .
b10 $
b10 (
b10 +
b0 *
0"
0,
1#
1-
1%
#960
0%
#965
b1 .
1"
1,
0#
0-
1%
#970
0%
#975
b10 .
b1 $
b1 (
b1 +
0"
0,
1#
1-
1%
#980
0%
#985
b1 .
1"
1,
0#
0-
1%
#990
0%
#995
b10 .
b0 $
b0 (
b0 +
0"
0,
1#
1-
1%
#1000
0%
#1005
b0 .
b10000 $
b10000 (
b10000 +
1"
1,
0#
0-
1%
#1010
0%
#1015
b1 .
1%
#1020
0%
#1025
b10 .
b1111 $
b1111 (
b1111 +
0"
0,
1#
1-
1%
b10011001001000 &
b10011001001000 )
#1030
0%
#1035
b1 .
1"
1,
0#
0-
1%
#1040
0%
#1045
b10 .
b1110 $
b1110 (
b1110 +
0"
0,
1#
1-
1%
#1050
0%
#1055
b1 .
1"
1,
0#
0-
1%
#1060
0%
#1065
1!
b10 .
b1101 $
b1101 (
b1101 +
b1 *
0"
0,
1#
1-
1%
#1070
0%
#1075
b1 .
1"
1,
0#
0-
1%
#1080
0%
#1085
0!
b10 .
b1100 $
b1100 (
b1100 +
b0 *
0"
0,
1#
1-
1%
#1090
0%
#1095
b1 .
1"
1,
0#
0-
1%
#1100
0%
#1105
b10 .
b1011 $
b1011 (
b1011 +
0"
0,
1#
1-
1%
#1110
0%
#1115
b1 .
1"
1,
0#
0-
1%
#1120
0%
#1125
1!
b10 .
b1010 $
b1010 (
b1010 +
b1 *
0"
0,
1#
1-
1%
#1130
0%
#1135
b1 .
1"
1,
0#
0-
1%
#1140
0%
#1145
b10 .
b1001 $
b1001 (
b1001 +
0"
0,
1#
1-
1%
#1150
0%
#1155
b1 .
1"
1,
0#
0-
1%
#1160
0%
#1165
0!
b10 .
b1000 $
b1000 (
b1000 +
b0 *
0"
0,
1#
1-
1%
#1170
0%
#1175
b1 .
1"
1,
0#
0-
1%
#1180
0%
#1185
b10 .
b111 $
b111 (
b111 +
0"
0,
1#
1-
1%
#1190
0%
#1195
b1 .
1"
1,
0#
0-
1%
#1200
0%
#1205
1!
b10 .
b110 $
b110 (
b110 +
b1 *
0"
0,
1#
1-
1%
#1210
0%
#1215
b1 .
1"
1,
0#
0-
1%
#1220
0%
#1225
0!
b10 .
b101 $
b101 (
b101 +
b0 *
0"
0,
1#
1-
1%
#1230
0%
#1235
b1 .
1"
1,
0#
0-
1%
#1240
0%
#1245
b10 .
b100 $
b100 (
b100 +
0"
0,
1#
1-
1%
#1250
0%
#1255
b1 .
1"
1,
0#
0-
1%
#1260
0%
#1265
1!
b10 .
b11 $
b11 (
b11 +
b1 *
0"
0,
1#
1-
1%
#1270
0%
#1275
b1 .
1"
1,
0#
0-
1%
#1280
0%
#1285
0!
b10 .
b10 $
b10 (
b10 +
b0 *
0"
0,
1#
1-
1%
#1290
0%
#1295
b1 .
1"
1,
0#
0-
1%
#1300
0%
#1305
b10 .
b1 $
b1 (
b1 +
0"
0,
1#
1-
1%
#1310
0%
#1315
b1 .
1"
1,
0#
0-
1%
#1320
0%
#1325
b10 .
b0 $
b0 (
b0 +
0"
0,
1#
1-
1%
#1330
0%
#1335
b0 .
b10000 $
b10000 (
b10000 +
1"
1,
0#
0-
1%
#1340
0%
#1345
b1 .
1%
#1350
0%
#1355
b10 .
b1111 $
b1111 (
b1111 +
0"
0,
1#
1-
1%
#1360
0%
b10011011110111 &
b10011011110111 )
#1365
b1 .
1"
1,
0#
0-
1%
#1370
0%
#1375
b10 .
b1110 $
b1110 (
b1110 +
0"
0,
1#
1-
1%
#1380
0%
#1385
b1 .
1"
1,
0#
0-
1%
#1390
0%
#1395
1!
b10 .
b1101 $
b1101 (
b1101 +
b1 *
0"
0,
1#
1-
1%
#1400
0%
#1405
b1 .
1"
1,
0#
0-
1%
#1410
0%
#1415
0!
b10 .
b1100 $
b1100 (
b1100 +
b0 *
0"
0,
1#
1-
1%
#1420
0%
#1425
b1 .
1"
1,
0#
0-
1%
#1430
0%
#1435
b10 .
b1011 $
b1011 (
b1011 +
0"
0,
1#
1-
1%
#1440
0%
#1445
b1 .
1"
1,
0#
0-
1%
#1450
0%
#1455
1!
b10 .
b1010 $
b1010 (
b1010 +
b1 *
0"
0,
1#
1-
1%
#1460
0%
#1465
b1 .
1"
1,
0#
0-
1%
#1470
0%
#1475
b10 .
b1001 $
b1001 (
b1001 +
0"
0,
1#
1-
1%
#1480
0%
#1485
b1 .
1"
1,
0#
0-
1%
#1490
0%
#1495
0!
b10 .
b1000 $
b1000 (
b1000 +
b0 *
0"
0,
1#
1-
1%
#1500
0%
#1505
b1 .
1"
1,
0#
0-
1%
#1510
0%
#1515
1!
b10 .
b111 $
b111 (
b111 +
b1 *
0"
0,
1#
1-
1%
#1520
0%
#1525
b1 .
1"
1,
0#
0-
1%
#1530
0%
#1535
b10 .
b110 $
b110 (
b110 +
0"
0,
1#
1-
1%
#1540
0%
#1545
b1 .
1"
1,
0#
0-
1%
#1550
0%
#1555
b10 .
b101 $
b101 (
b101 +
0"
0,
1#
1-
1%
#1560
0%
#1565
b1 .
1"
1,
0#
0-
1%
#1570
0%
#1575
b10 .
b100 $
b100 (
b100 +
0"
0,
1#
1-
1%
#1580
0%
#1585
b1 .
1"
1,
0#
0-
1%
#1590
0%
#1595
0!
b10 .
b11 $
b11 (
b11 +
b0 *
0"
0,
1#
1-
1%
#1600
0%
#1605
b1 .
1"
1,
0#
0-
1%
#1610
0%
#1615
1!
b10 .
b10 $
b10 (
b10 +
b1 *
0"
0,
1#
1-
1%
#1620
0%
#1625
b1 .
1"
1,
0#
0-
1%
#1630
0%
#1635
b10 .
b1 $
b1 (
b1 +
0"
0,
1#
1-
1%
#1640
0%
#1645
b1 .
1"
1,
0#
0-
1%
#1650
0%
#1655
b10 .
b0 $
b0 (
b0 +
0"
0,
1#
1-
1%
#1660
0%
#1665
b0 .
b10000 $
b10000 (
b10000 +
1"
1,
0#
0-
1%
#1670
0%
#1675
b1 .
1%
#1680
0%
#1685
0!
b10 .
b1111 $
b1111 (
b1111 +
b0 *
0"
0,
1#
1-
1%
#1690
0%
#1695
b1 .
1"
1,
0#
0-
1%
#1700
0%
#1705
b10 .
b1110 $
b1110 (
b1110 +
0"
0,
1#
1-
1%
#1710
0%
#1715
b1 .
1"
1,
0#
0-
1%
#1720
0%
#1725
1!
b10 .
b1101 $
b1101 (
b1101 +
b1 *
0"
0,
1#
1-
1%
#1730
0%
#1735
b1 .
1"
1,
0#
0-
1%
#1740
0%
#1745
0!
b10 .
b1100 $
b1100 (
b1100 +
b0 *
0"
0,
1#
1-
1%
#1750
0%
#1755
b1 .
1"
1,
0#
0-
1%
#1760
0%
#1765
b10 .
b1011 $
b1011 (
b1011 +
0"
0,
1#
1-
1%
#1770
0%
#1775
b1 .
1"
1,
0#
0-
1%
#1780
0%
#1785
1!
b10 .
b1010 $
b1010 (
b1010 +
b1 *
0"
0,
1#
1-
1%
#1790
0%
#1795
b1 .
1"
1,
0#
0-
1%
#1800
0%
#1805
b10 .
b1001 $
b1001 (
b1001 +
0"
0,
1#
1-
1%
#1810
0%
#1815
b1 .
1"
1,
0#
0-
1%
#1820
0%
#1825
0!
b10 .
b1000 $
b1000 (
b1000 +
b0 *
0"
0,
1#
1-
1%
#1830
0%
#1835
b1 .
1"
1,
0#
0-
1%
#1840
0%
#1845
1!
b10 .
b111 $
b111 (
b111 +
b1 *
0"
0,
1#
1-
1%
#1850
0%
#1855
b1 .
1"
1,
0#
0-
1%
#1860
0%
#1865
b10 .
b110 $
b110 (
b110 +
0"
0,
1#
1-
1%
#1870
0%
#1875
b1 .
1"
1,
0#
0-
1%
#1880
0%
#1885
b10 .
b101 $
b101 (
b101 +
0"
0,
1#
1-
1%
#1890
0%
#1895
b1 .
1"
1,
0#
0-
1%
#1900
0%
#1905
b10 .
b100 $
b100 (
b100 +
0"
0,
1#
1-
1%
#1910
0%
#1915
b1 .
1"
1,
0#
0-
1%
#1920
0%
#1925
0!
b10 .
b11 $
b11 (
b11 +
b0 *
0"
0,
1#
1-
1%
#1930
0%
#1935
b1 .
1"
1,
0#
0-
1%
#1940
0%
#1945
1!
b10 .
b10 $
b10 (
b10 +
b1 *
0"
0,
1#
1-
1%
#1950
0%
#1955
b1 .
1"
1,
0#
0-
1%
#1960
0%
#1965
b10 .
b1 $
b1 (
b1 +
0"
0,
1#
1-
1%
#1970
0%
#1975
b1 .
1"
1,
0#
0-
1%
#1980
0%
#1985
b10 .
b0 $
b0 (
b0 +
0"
0,
1#
1-
1%
#1990
0%
#1995
b0 .
b10000 $
b10000 (
b10000 +
1"
1,
0#
0-
1%
